graphml/__init__.py
graphml/_about.py
graphml/_cli.py
graphml-0.0.1.dist-info/LICENSE
graphml-0.0.1.dist-info/METADATA
graphml-0.0.1.dist-info/WHEEL
graphml-0.0.1.dist-info/entry_points.txt
graphml-0.0.1.dist-info/top_level.txt
graphml-0.0.1.dist-info/RECORD
